torchlet/__init__.py
torchlet/_tensor.py
torchlet/autodiff.py
torchlet/dev_utils.py
torchlet/nn/__init__.py
torchlet/nn/activations.py
torchlet/nn/containers.py
torchlet/nn/layers.py
torchlet/nn/module.py
torchlet/optim/__init__.py
torchlet/optim/optimizer.py
torchlet/optim/sgd.py
torchlet/scalar_ops.py
torchlet/tensor_data.py
torchlet/tensor_functions.py
torchlet/tensor_ops.py
torchlet-0.1.0.dist-info/LICENSE
torchlet-0.1.0.dist-info/METADATA
torchlet-0.1.0.dist-info/WHEEL
torchlet-0.1.0.dist-info/RECORD
