Metadata-Version: 2.1
Name: torchlet
Version: 0.1.0
Summary: A small, minimalist variant of PyTorch.
Author: Cem Alpturk
Author-email: cem.alpturk@gmail.com
Requires-Python: >=3.11,<4.0
Classifier: Programming Language :: Python :: 3
Classifier: Programming Language :: Python :: 3.11
Classifier: Programming Language :: Python :: 3.12
Requires-Dist: numpy (>=2.0.1,<3.0.0)
